{
    "lstsearchresualt": [
        {
            "id": 11731209,
            "title": "پتوشور پاکیزان 30 کیلویی ",
            "titlefa": "",
            "link": "/مشخصات_پتوشور-پاکیزان-30-کیلویی~id~11731209",
            "esrever": "90213711~di~ییولیک-03-نازیکاپ-روشوتپ_تاصخشم/",
            "image": "https://files.emalls.ir/files/Products/automatic/11731209/0obuqpon_thumb2.jpg",
            "category": null,
            "rate": null,
            "offcount": "10",
            "price": "۵,۹۰۰,۰۰۰",
            "pprice": null,
            "discountpercent": null,
            "maxprice": "۸,۲۵۹,۰۰۰",
            "lupdate": "(۷ ساعت پیش)",
            "buyTitle": "",
            "buyLink": "",
            "spec": false,
            "used": false
        },
        {
            "id": 22518120,
            "title": "گاوصندوق کتابی مخفی سدید مدل Safebox",
            "titlefa": "-",
            "link": "/مشخصات_گاوصندوق-کتابی-مخفی-سدید-مدل-Safebox~id~22518120",
            "esrever": "02181522~di~xobefaS-لدم-دیدس-یفخم-یباتک-قودنصواگ_تاصخشم/",
            "image": "https://files.emalls.ir/files/Products/automatic/22518120/xjztzzc2_thumb2.jpg",
            "category": null,
            "rate": null,
            "offcount": "13",
            "price": "۹۸۵,۰۰۰",
            "pprice": "۱,۱۰۰,۰۰۰",
            "discountpercent": "10",
            "maxprice": "۲,۱۰۰,۰۰۰",
            "lupdate": "(۷ ساعت پیش)",
            "buyTitle": "",
            "buyLink": "",
            "spec": false,
            "used": false
        },
        {
            "id": 23832479,
            "title": "آیپد 13 اینچی اپل مدل Apple iPad Pro 13 WIFI 2024 با ظرفیت 512 گیگابایت و رم 8 گیگابایت",
            "titlefa": "آیپد 13 اینچی اپل مدل Apple iPad Pro 13 WIFI 2024 با ظرفیت 512 گیگابایت و رم 8 گیگابایت",
            "link": "/مشخصات_Apple-iPad-Pro-13-WIFI-2024-8-512GB-Tablet~id~23832479",
            "esrever": "97423832~di~telbaT-BG215-8-4202-IFIW-31-orP-daPi-elppA_تاصخشم/",
            "image": "https://files.emalls.ir/files/Products/automatic/23832479/selzl2sm_thumb2.jpg",
            "category": null,
            "rate": null,
            "offcount": "26",
            "price": "۱۰۶,۹۹۰,۰۰۰",
            "pprice": null,
            "discountpercent": null,
            "maxprice": "۱۱۸,۰۰۰,۰۰۰",
            "lupdate": "(۷ ساعت پیش)",
            "buyTitle": "",
            "buyLink": "",
            "spec": false,
            "used": false
        },
        {
            "id": 1977383,
            "title": "توالت فرنگی مروارید مدل کرون",
            "titlefa": "",
            "link": "/مشخصات_توالت-فرنگی-مروارید-مدل-کرون~id~1977383",
            "esrever": "3837791~di~نورک-لدم-دیراورم-یگنرف-تلاوت_تاصخشم/",
            "image": "https://files.emalls.ir/files/Products/automatic/1977383/1rpjaqbh_thumb2.jpg",
            "category": null,
            "rate": null,
            "offcount": "35",
            "price": "۶,۳۱۵,۰۰۰",
            "pprice": "۶,۶۴۸,۴۰۰",
            "discountpercent": "5",
            "maxprice": "۹,۳۶۲,۱۰۰",
            "lupdate": "(۷ ساعت پیش)",
            "buyTitle": "",
            "buyLink": "",
            "spec": false,
            "used": false
        },
        {
            "id": 10747756,
            "title": "کیس کامپیوتر گرین مدل GRIFFIN G4",
            "titlefa": "-",
            "link": "/مشخصات_کیس-کامپیوتر-گرین-مدل-GRIFFIN-G4~id~10747756",
            "esrever": "65774701~di~4G-NIFFIRG-لدم-نیرگ-رتویپماک-سیک_تاصخشم/",
            "image": "https://files.emalls.ir/files/Products/automatic/10747756/pcaaglui_thumb2.jpg",
            "category": null,
            "rate": null,
            "offcount": "60",
            "price": "۴,۲۹۰,۰۰۰",
            "pprice": null,
            "discountpercent": null,
            "maxprice": "۵,۱۴۰,۰۰۰",
            "lupdate": "(۷ ساعت پیش)",
            "buyTitle": "",
            "buyLink": "",
            "spec": false,
            "used": false
        },
        {
            "id": 4953042,
            "title": "اسپرسوساز دلونگی مدل DELONGHI EC785",
            "titlefa": "Delonghi dedica Metalics 785BG",
            "link": "/مشخصات_اسپرسوساز-دلونگی-مدل-DELONGHI-EC785~id~4953042",
            "esrever": "2403594~di~587CE-IHGNOLED-لدم-یگنولد-زاسوسرپسا_تاصخشم/",
            "image": "https://files.emalls.ir/files/Products/automatic/4953042/syjwpck0_thumb2.jpg",
            "category": null,
            "rate": null,
            "offcount": "43",
            "price": "۱۰,۵۴۹,۰۰۰",
            "pprice": null,
            "discountpercent": null,
            "maxprice": "۱۷,۹۶۸,۷۵۰",
            "lupdate": "(۷ ساعت پیش)",
            "buyTitle": "",
            "buyLink": "",
            "spec": false,
            "used": false
        },
        {
            "id": 4506780,
            "title": "کولر گازی 12000 زانتی Zaneti دیواری سرمایش و گرمایش",
            "titlefa": "کولر گازی 12000 زانتی Zaneti دیواری سرمایش و گرمایش",
            "link": "/مشخصات_ZMSA-12HO1RAFA~id~4506780",
            "esrever": "0876054~di~AFAR1OH21-ASMZ_تاصخشم/",
            "image": "https://files.emalls.ir/files/Products/automatic/4506780/yvmfolrr_thumb2.jpg",
            "category": null,
            "rate": null,
            "offcount": "18",
            "price": "۱۴,۹۰۰,۰۰۰",
            "pprice": null,
            "discountpercent": null,
            "maxprice": "۲۹,۰۰۰,۰۰۰",
            "lupdate": "(۷ ساعت پیش)",
            "buyTitle": "",
            "buyLink": "",
            "spec": false,
            "used": false
        },
        {
            "id": 988413,
            "title": "جارو شارژی بلک اند دکر مدل PV1420",
            "titlefa": "Black And Decker PV1420 Chargeable Vacuum Cleaner",
            "link": "/مشخصات_جارو-شارژی-بلک-اند-دکر-مدل-PV1420~id~988413",
            "esrever": "314889~di~0241VP-لدم-رکد-دنا-کلب-یژراش-وراج_تاصخشم/",
            "image": "https://files.emalls.ir/files/products/automatic/988413/y44ebuqx_thumb2.jpg",
            "category": null,
            "rate": null,
            "offcount": "75",
            "price": "۳,۱۹۹,۰۰۰",
            "pprice": null,
            "discountpercent": null,
            "maxprice": "۳۹,۹۰۰,۰۰۰",
            "lupdate": "(۷ ساعت پیش)",
            "buyTitle": "",
            "buyLink": "",
            "spec": false,
            "used": false
        },
        {
            "id": 2566889,
            "title": "پلوپز تفال RK7088",
            "titlefa": "7088",
            "link": "/مشخصات_پلوپز-تفال-RK7088~id~2566889",
            "esrever": "9886652~di~8807KR-لافت-زپولپ_تاصخشم/",
            "image": "https://files.emalls.ir/files/Products/automatic/2566889/bzppsodj_thumb2.jpg",
            "category": null,
            "rate": null,
            "offcount": "27",
            "price": "۴,۹۵۶,۸۰۰",
            "pprice": null,
            "discountpercent": null,
            "maxprice": "۸,۸۳۰,۰۰۰",
            "lupdate": "(۷ ساعت پیش)",
            "buyTitle": "",
            "buyLink": "",
            "spec": false,
            "used": false
        },
        {
            "id": 1300754,
            "title": " روغن مخصوص سرخ کردنی بهار مدل الماس مقدار 1800 میلی لیتر",
            "titlefa": "Bahar Deep Frying Almas Oil  1.8 ",
            "link": "/مشخصات_-روغن-مخصوص-سرخ-کردنی-بهار-مدل-الماس-مقدار-1800-میلی-لیتر~id~1300754",
            "esrever": "4570031~di~رتیل-یلیم-0081-رادقم-ساملا-لدم-راهب-یندرک-خرس-صوصخم-نغور-_تاصخشم/",
            "image": "https://files.emalls.ir/files/products/automatic/1300754/2hnoetgg_thumb2.jpg",
            "category": null,
            "rate": null,
            "offcount": "3",
            "price": "۱۲۶,۰۰۰",
            "pprice": null,
            "discountpercent": null,
            "maxprice": "۷۵۶,۰۰۰",
            "lupdate": "(۷ ساعت پیش)",
            "buyTitle": "",
            "buyLink": "",
            "spec": false,
            "used": false
        },
        {
            "id": 25365930,
            "title": "ماشین لباسشویی ۸ کیلویی دوو سانسو sunsu مدل LM-811S",
            "titlefa": "",
            "link": "/مشخصات_ماشین-لباسشویی-۸-کیلویی-دوو-سانسو-sunsu-مدل-LM-811S~id~25365930",
            "esrever": "03956352~di~S118-ML-لدم-usnus-وسناس-وود-ییولیک-۸-ییوشسابل-نیشام_تاصخشم/",
            "image": "https://files.emalls.ir/files/Products/automatic/25365930/k22jerbt_thumb2.png",
            "category": null,
            "rate": null,
            "offcount": "20",
            "price": "۱۹,۷۸۰,۰۰۰",
            "pprice": null,
            "discountpercent": null,
            "maxprice": "۲۲,۶۹۰,۱۷۰",
            "lupdate": "(۷ ساعت پیش)",
            "buyTitle": "",
            "buyLink": "",
            "spec": false,
            "used": false
        },
        {
            "id": 1840119,
            "title": "باتری گوشی هوآوی وای 7 پرایم",
            "titlefa": "باتری گوشی هوآوی وای 7 پرایم",
            "link": "/مشخصات_باتری-گوشی-هواوی-وای-7-پرایم-Huawei-Y7-Prime~id~1840119",
            "esrever": "9110481~di~emirP-7Y-iewauH-میارپ-7-یاو-یواوه-یشوگ-یرتاب_تاصخشم/",
            "image": "https://files.emalls.ir/files/Products/automatic/1840119/wkxpcqvo_thumb2.jpg",
            "category": null,
            "rate": null,
            "offcount": "12",
            "price": "۲۷۰,۰۰۰",
            "pprice": null,
            "discountpercent": null,
            "maxprice": "۶۲۵,۰۰۰",
            "lupdate": "(۷ ساعت پیش)",
            "buyTitle": "",
            "buyLink": "",
            "spec": false,
            "used": false
        },
        {
            "id": 1111171,
            "title": "کارواش 1400 وات توسن - 1114CPWX",
            "titlefa": "",
            "link": "/مشخصات_کارواش-1400-وات-توسن--1114CPWX~id~1111171",
            "esrever": "1711111~di~XWPC4111--نسوت-تاو-0041-شاوراک_تاصخشم/",
            "image": "https://files.emalls.ir/files/products/automatic/1111171/ly4uotnh_thumb2.jpg",
            "category": null,
            "rate": null,
            "offcount": "17",
            "price": "۴,۹۲۶,۰۰۰",
            "pprice": null,
            "discountpercent": null,
            "maxprice": "۵۶,۶۵۸,۸۵۴",
            "lupdate": "(۷ ساعت پیش)",
            "buyTitle": "",
            "buyLink": "",
            "spec": false,
            "used": false
        },
        {
            "id": 1260802,
            "title": "فلاسک چای مسافرتی 1 لیتری یونیک",
            "titlefa": "",
            "link": "/مشخصات_فلاسک-چای-مسافرتی-1-لیتری-یونیک~id~1260802",
            "esrever": "2080621~di~کینوی-یرتیل-1-یترفاسم-یاچ-کسالف_تاصخشم/",
            "image": "https://files.emalls.ir/files/products/automatic/1260802/nagzhf5y_thumb2.jpg",
            "category": null,
            "rate": null,
            "offcount": "27",
            "price": "۲۰۹,۰۰۰",
            "pprice": "۲۳۹,۹۰۰",
            "discountpercent": "13",
            "maxprice": "۱,۲۵۰,۰۰۰",
            "lupdate": "(۷ ساعت پیش)",
            "buyTitle": "",
            "buyLink": "",
            "spec": false,
            "used": false
        },
        {
            "id": 4126810,
            "title": "مینی واش فریدولین SWT35",
            "titlefa": "",
            "link": "/مشخصات_مینی-واش-فریدولین-SWT35~id~4126810",
            "esrever": "0186214~di~53TWS-نیلودیرف-شاو-ینیم_تاصخشم/",
            "image": "https://files.emalls.ir/files/Products/automatic/4126810/fn5vehh2_thumb2.jpg",
            "category": null,
            "rate": null,
            "offcount": "12",
            "price": "۴,۵۵۰,۰۰۰",
            "pprice": "۵,۳۵۰,۰۰۰",
            "discountpercent": "15",
            "maxprice": "۶,۹۰۰,۰۰۰",
            "lupdate": "(۷ ساعت پیش)",
            "buyTitle": "",
            "buyLink": "",
            "spec": false,
            "used": false
        },
        {
            "id": 15438365,
            "title": "دستگاه اینورتر آرواهوم ARC 200 IGBT مدل 2178",
            "titlefa": "",
            "link": "/مشخصات_دستگاه-اینورتر-آرواهوم-ARC-200-IGBT-مدل-2178~id~15438365",
            "esrever": "56383451~di~8712-لدم-TBGI-002-CRA-موهاورآ-رترونیا-هاگتسد_تاصخشم/",
            "image": "https://files.emalls.ir/files/Products/automatic/15438365/jmd33y1k_thumb2.jpg",
            "category": null,
            "rate": null,
            "offcount": "30",
            "price": "۳,۳۶۷,۰۰۰",
            "pprice": "۵,۰۰۰,۰۰۰",
            "discountpercent": "33",
            "maxprice": "۵۷۰,۷۷۸,۲۰۸",
            "lupdate": "(۷ ساعت پیش)",
            "buyTitle": "",
            "buyLink": "",
            "spec": false,
            "used": false
        },
        {
            "id": 690458,
            "title": "پرینتر چندکاره لیزری Hp LaserJet Pro MFP M26a",
            "titlefa": "پرینتر چندکاره لیزری Hp LaserJet Pro MFP M26a",
            "link": "/مشخصات_HP-LaserJet-Pro-MFP-M26a-Multifunction-Laser-Printer~id~690458",
            "esrever": "854096~di~retnirP-resaL-noitcnufitluM-a62M-PFM-orP-teJresaL-PH_تاصخشم/",
            "image": "https://files.emalls.ir/files/Products/automatic/690458/j3bw132h_thumb2.jpg",
            "category": null,
            "rate": null,
            "offcount": "66",
            "price": "۱۴,۵۰۰,۰۰۰",
            "pprice": null,
            "discountpercent": null,
            "maxprice": "۳۹,۰۰۰,۰۰۰",
            "lupdate": "(۷ ساعت پیش)",
            "buyTitle": "",
            "buyLink": "",
            "spec": false,
            "used": false
        },
        {
            "id": 3262139,
            "title": "دستگاه ایکس وی آر 8 کانال داهوا مدل DH-XVR1B08-I",
            "titlefa": "دستگاه ایکس وی آر 8 کانال داهوا مدل DH-XVR1B08-I",
            "link": "/مشخصات_ضبط-کننده-ویدیویی-داهوا-مدل-XVR1B08-I~id~3262139",
            "esrever": "9312623~di~I-80B1RVX-لدم-اوهاد-ییویدیو-هدننک-طبض_تاصخشم/",
            "image": "https://files.emalls.ir/files/Products/automatic/3262139/uycsny5d_thumb2.jpg",
            "category": null,
            "rate": null,
            "offcount": "68",
            "price": "۱,۹۰۰,۰۰۰",
            "pprice": "۲,۴۵۰,۰۰۰",
            "discountpercent": "22",
            "maxprice": "۵,۷۷۵,۰۰۰",
            "lupdate": "(۷ ساعت پیش)",
            "buyTitle": "",
            "buyLink": "",
            "spec": false,
            "used": false
        },
        {
            "id": 8184123,
            "title": "غذا خشک گربه مونلو مدل Salmon  Chicken وزن 15 کیلوگرم",
            "titlefa": "-",
            "link": "/مشخصات_غذا-خشک-گربه-مونلو-مدل-Salmon-Chicken-وزن-15-کیلوگرم~id~8184123",
            "esrever": "3214818~di~مرگولیک-51-نزو-nekcihC-nomlaS-لدم-ولنوم-هبرگ-کشخ-اذغ_تاصخشم/",
            "image": "https://files.emalls.ir/files/Products/automatic/8184123/kqq02xkr_thumb2.jpg",
            "category": null,
            "rate": null,
            "offcount": "19",
            "price": "۵,۷۰۰,۰۰۰",
            "pprice": null,
            "discountpercent": null,
            "maxprice": "۸,۴۰۰,۰۰۰",
            "lupdate": "(۷ ساعت پیش)",
            "buyTitle": "",
            "buyLink": "",
            "spec": false,
            "used": false
        },
        {
            "id": 25132971,
            "title": "دیسک بازی EA Sports FC 25  مخصوص PS4",
            "titlefa": "EA Sports FC 25 PS4",
            "link": "/مشخصات_دیسک-بازی-EA-Sports-FC-25-مخصوص-PS4~id~25132971",
            "esrever": "17923152~di~4SP-صوصخم-52-CF-stropS-AE-یزاب-کسید_تاصخشم/",
            "image": "https://files.emalls.ir/files/Products/automatic/25132971/xz2q0uxy_thumb2.jpg",
            "category": null,
            "rate": null,
            "offcount": "13",
            "price": "۳,۴۳۰,۰۰۰",
            "pprice": null,
            "discountpercent": null,
            "maxprice": "۳,۹۳۰,۰۰۰",
            "lupdate": "(۷ ساعت پیش)",
            "buyTitle": "",
            "buyLink": "",
            "spec": false,
            "used": false
        },
        {
            "id": 344068,
            "title": "سیستم کنفرانس ویدئو گروهی لاجیتک",
            "titlefa": "سیستم کنفرانس ویدئو گروهی لاجیتک",
            "link": "/مشخصات_Logitech-Group-Video-Conferencing-System~id~344068",
            "esrever": "860443~di~metsyS-gnicnerefnoC-oediV-puorG-hcetigoL_تاصخشم/",
            "image": "https://files.emalls.ir/files/Products/automatic/344068/wj23avjc_thumb2.jpg",
            "category": null,
            "rate": null,
            "offcount": "27",
            "price": "۴۶,۵۰۰,۰۰۰",
            "pprice": null,
            "discountpercent": null,
            "maxprice": "۷۹,۰۰۰,۰۰۰",
            "lupdate": "(۷ ساعت پیش)",
            "buyTitle": "",
            "buyLink": "",
            "spec": false,
            "used": false
        },
        {
            "id": 13769697,
            "title": "سرویس روتختی مدل فرنو دو نفره شش تکه",
            "titlefa": "-",
            "link": "/مشخصات_سرویس-روتختی-مدل-فرنو-دو-نفره-شش-تکه~id~13769697",
            "esrever": "79696731~di~هکت-شش-هرفن-ود-ونرف-لدم-یتختور-سیورس_تاصخشم/",
            "image": "https://files.emalls.ir/files/Products/automatic/13769697/huo1ywzo_thumb2.jpg",
            "category": null,
            "rate": null,
            "offcount": "3",
            "price": "۳۶۱,۹۰۰",
            "pprice": null,
            "discountpercent": null,
            "maxprice": "۲,۰۰۰,۰۰۰",
            "lupdate": "(۷ ساعت پیش)",
            "buyTitle": "",
            "buyLink": "",
            "spec": false,
            "used": false
        },
        {
            "id": 12084685,
            "title": "کیس کامپیوتر گرین GREEN GRIFFIN G7 RGB",
            "titlefa": "کیس کامپیوتر گرین GREEN GRIFFIN G7 RGB",
            "link": "/مشخصات_Green-GRIFFIN-G7-Computer-Case~id~12084685",
            "esrever": "58648021~di~esaC-retupmoC-7G-NIFFIRG-neerG_تاصخشم/",
            "image": "https://files.emalls.ir/files/Products/automatic/12084685/z10aw44u_thumb2.jpg",
            "category": null,
            "rate": null,
            "offcount": "51",
            "price": "۶,۴۹۸,۰۰۰",
            "pprice": null,
            "discountpercent": null,
            "maxprice": "۷,۵۵۰,۰۰۰",
            "lupdate": "(۷ ساعت پیش)",
            "buyTitle": "",
            "buyLink": "",
            "spec": false,
            "used": false
        },
        {
            "id": 4354769,
            "title": "تلفن تحت شبکه یالینک Yealink SIP T31P",
            "titlefa": "تلفن تحت شبکه یالینک Yealink SIP T31P",
            "link": "/مشخصات_IP-PHONE-YEALINK-T31P~id~4354769",
            "esrever": "9674534~di~P13T-KNILAEY-ENOHP-PI_تاصخشم/",
            "image": "https://files.emalls.ir/files/Products/automatic/4354769/pwq0cbzt_thumb2.jpg",
            "category": null,
            "rate": null,
            "offcount": "56",
            "price": "۱,۷۰۰,۰۰۰",
            "pprice": null,
            "discountpercent": null,
            "maxprice": "۳,۵۰۰,۰۰۰",
            "lupdate": "(۷ ساعت پیش)",
            "buyTitle": "",
            "buyLink": "",
            "spec": false,
            "used": false
        },
        {
            "id": 19029228,
            "title": "مانیتور گیمینگ 40 اینچ MSI مدل MAG401QR",
            "titlefa": "مانیتور گیمینگ 40 اینچ MSI مدل MAG401QR",
            "link": "/مشخصات_MSI-MAG401QR-Gaming-40-Inch-Monitor~id~19029228",
            "esrever": "82292091~di~rotinoM-hcnI-04-gnimaG-RQ104GAM-ISM_تاصخشم/",
            "image": "https://files.emalls.ir/files/Products/automatic/19029228/sj2mttcx_thumb2.jpg",
            "category": null,
            "rate": null,
            "offcount": "31",
            "price": "۳۵,۰۰۰,۰۰۰",
            "pprice": null,
            "discountpercent": null,
            "maxprice": "۴۴,۰۰۰,۰۰۰",
            "lupdate": "(۷ ساعت پیش)",
            "buyTitle": "",
            "buyLink": "",
            "spec": false,
            "used": false
        },
        {
            "id": 2700801,
            "title": "پرینتر لیزری اچ پی مدل LaserJet Pro M15a",
            "titlefa": "پرینتر لیزری اچ پی مدل LaserJet Pro M15a",
            "link": "/مشخصات_HP-LaserJet-Pro-M15a-Laser-Printer~id~2700801",
            "esrever": "1080072~di~retnirP-resaL-a51M-orP-teJresaL-PH_تاصخشم/",
            "image": "https://files.emalls.ir/files/Products/automatic/2700801/j3xnnxt0_thumb2.jpg",
            "category": null,
            "rate": null,
            "offcount": "70",
            "price": "۹,۸۵۰,۰۰۰",
            "pprice": null,
            "discountpercent": null,
            "maxprice": "۱۶,۹۰۰,۰۰۰",
            "lupdate": "(۷ ساعت پیش)",
            "buyTitle": "",
            "buyLink": "",
            "spec": false,
            "used": false
        },
        {
            "id": 128110,
            "title": "چرخ گوشت پارس خزر مدل MG-1600P",
            "titlefa": "",
            "link": "/مشخصات_چرخ-گوشت-پارس-خزر-مدل-MG-1600P~id~128110",
            "esrever": "011821~di~P0061-GM-لدم-رزخ-سراپ-تشوگ-خرچ_تاصخشم/",
            "image": "https://files.emalls.ir/files/products/automatic/712025_thumb2.jpg",
            "category": null,
            "rate": null,
            "offcount": "39",
            "price": "۴,۵۸۵,۰۰۰",
            "pprice": null,
            "discountpercent": null,
            "maxprice": "۶,۸۵۴,۱۲۵",
            "lupdate": "(۷ ساعت پیش)",
            "buyTitle": "",
            "buyLink": "",
            "spec": false,
            "used": false
        },
        {
            "id": 21512410,
            "title": "اسپرسوساز مباشی مدل 2108",
            "titlefa": "",
            "link": "/مشخصات_اسپرسوساز-مباشی-مدل-2108~id~21512410",
            "esrever": "01421512~di~8012-لدم-یشابم-زاسوسرپسا_تاصخشم/",
            "image": "https://files.emalls.ir/files/Products/automatic/21512410/butkhiql_thumb2.jpg",
            "category": null,
            "rate": null,
            "offcount": "34",
            "price": "۱۱,۵۳۰,۰۰۰",
            "pprice": null,
            "discountpercent": null,
            "maxprice": "۱۷,۹۰۹,۰۰۰",
            "lupdate": "(۷ ساعت پیش)",
            "buyTitle": "",
            "buyLink": "",
            "spec": false,
            "used": false
        },
        {
            "id": 14318129,
            "title": "ساعت هوشمند Hk9pro دارای قطب نمای فعال",
            "titlefa": "Wearfit HK9 Pro Smart Watch",
            "link": "/مشخصات_ساعت-هوشمند-Hk9pro-دارای-قطب-نمای-فعال~id~14318129",
            "esrever": "92181341~di~لاعف-یامن-بطق-یاراد-orp9kH-دنمشوه-تعاس_تاصخشم/",
            "image": "https://files.emalls.ir/files/Products/automatic/14318129/ntgzt1f5_thumb2.jpg",
            "category": null,
            "rate": null,
            "offcount": "20",
            "price": "۹۵۰,۰۰۰",
            "pprice": "۱,۰۶۸,۰۰۰",
            "discountpercent": "11",
            "maxprice": "۲,۴۰۰,۰۰۰",
            "lupdate": "(۷ ساعت پیش)",
            "buyTitle": "",
            "buyLink": "",
            "spec": false,
            "used": false
        },
        {
            "id": 2382841,
            "title": "ماشین اصلاح موی صورت یاندو  مدل Sv-w301u",
            "titlefa": "-",
            "link": "/مشخصات_ماشین-اصلاح-موی-صورت-یاندو-مدل-Sv-w301u~id~2382841",
            "esrever": "1482832~di~u103w-vS-لدم-ودنای-تروص-یوم-حالصا-نیشام_تاصخشم/",
            "image": "https://files.emalls.ir/files/Products/automatic/2382841/imc2odxa_thumb2.jpg",
            "category": null,
            "rate": null,
            "offcount": "28",
            "price": "۲۸۲,۰۰۰",
            "pprice": null,
            "discountpercent": null,
            "maxprice": "۶۹۰,۰۰۰",
            "lupdate": "(۷ ساعت پیش)",
            "buyTitle": "",
            "buyLink": "",
            "spec": false,
            "used": false
        },
        {
            "id": 19472890,
            "title": "ساعت هوشمند شیائومی Redmi Watch 4",
            "titlefa": "",
            "link": "/مشخصات_ساعت-هوشمند-شیائومی-Redmi-Watch-4~id~19472890",
            "esrever": "09827491~di~4-hctaW-imdeR-یموئایش-دنمشوه-تعاس_تاصخشم/",
            "image": "https://files.emalls.ir/files/Products/automatic/19472890/bon5nsii_thumb2.png",
            "category": null,
            "rate": null,
            "offcount": "40",
            "price": "۴,۹۱۵,۸۹۰",
            "pprice": null,
            "discountpercent": null,
            "maxprice": "۱۱,۹۴۶,۱۵۰",
            "lupdate": "(۷ ساعت پیش)",
            "buyTitle": "",
            "buyLink": "",
            "spec": false,
            "used": false
        },
        {
            "id": 5847774,
            "title": "کاله برگر 100 درصد گوشت قرمز پمینا - 500 گرم",
            "titlefa": "-",
            "link": "/مشخصات_کاله-برگر-100-درصد-گوشت-قرمز-پمینا--500-گرم~id~5847774",
            "esrever": "4777485~di~مرگ-005--انیمپ-زمرق-تشوگ-دصرد-001-رگرب-هلاک_تاصخشم/",
            "image": "https://files.emalls.ir/files/Products/automatic/5847774/rdjz0cnv_thumb2.jpg",
            "category": null,
            "rate": null,
            "offcount": "2",
            "price": "۲۶۳,۰۰۰",
            "pprice": null,
            "discountpercent": null,
            "maxprice": "۲۶۳,۰۰۰",
            "lupdate": "(۷ ساعت پیش)",
            "buyTitle": "",
            "buyLink": "",
            "spec": false,
            "used": false
        },
        {
            "id": 67361,
            "title": "کارت شبکه USB و بی‌سیم تی پی-لینک مدل TL-WN722N",
            "titlefa": "کارت شبکه USB و بی‌سیم تی پی-لینک مدل TL-WN722N",
            "link": "/مشخصات_TP-LINK-TL-WN722N-150Mbps-High-Gain-Wireless-USB-Adapter~id~67361",
            "esrever": "16376~di~retpadA-BSU-sseleriW-niaG-hgiH-spbM051-N227NW-LT-KNIL-PT_تاصخشم/",
            "image": "https://files.emalls.ir/files/Products/automatic/67361/zmhgm2vs_thumb2.jpg",
            "category": null,
            "rate": null,
            "offcount": "25",
            "price": "۶۲۰,۰۰۰",
            "pprice": null,
            "discountpercent": null,
            "maxprice": "۱,۱۲۰,۰۰۰",
            "lupdate": "(۷ ساعت پیش)",
            "buyTitle": "",
            "buyLink": "",
            "spec": false,
            "used": false
        },
        {
            "id": 4673901,
            "title": " ماشین مجیک کار",
            "titlefa": "",
            "link": "/مشخصات_-ماشین-مجیک-کار~id~4673901",
            "esrever": "1093764~di~راک-کیجم-نیشام-_تاصخشم/",
            "image": "https://files.emalls.ir/files/Products/automatic/4673901/x213ynxb_thumb2.jpg",
            "category": null,
            "rate": null,
            "offcount": "17",
            "price": "۸۸۰,۰۰۰",
            "pprice": "۹۸۰,۰۰۰",
            "discountpercent": "10",
            "maxprice": "۱,۴۴۰,۰۰۰",
            "lupdate": "(۷ ساعت پیش)",
            "buyTitle": "",
            "buyLink": "",
            "spec": false,
            "used": false
        },
        {
            "id": 775480,
            "title": "جارو برقی پارس خزر مدل Turbo 2000",
            "titlefa": "جارو برقی پارس خزر مدل Turbo 2000",
            "link": "/مشخصات_جارو-برقی-پارس-خزر-مدل-توربو-2000~id~775480",
            "esrever": "084577~di~0002-وبروت-لدم-رزخ-سراپ-یقرب-وراج_تاصخشم/",
            "image": "https://files.emalls.ir/files/products/automatic/775480/d1roimo5_thumb2.jpg",
            "category": null,
            "rate": null,
            "offcount": "42",
            "price": "۵,۲۵۰,۰۰۰",
            "pprice": null,
            "discountpercent": null,
            "maxprice": "۸,۴۰۸,۰۰۰",
            "lupdate": "(۷ ساعت پیش)",
            "buyTitle": "",
            "buyLink": "",
            "spec": false,
            "used": false
        },
        {
            "id": 4267268,
            "title": "ماشین اصلاح خط زن وی جی آر مدل VGR V-062",
            "titlefa": "VGR V-062 hair trimmer",
            "link": "/مشخصات_ماشین-اصلاح-خط-زن-وی-جی-آر-مدل-VGR-V-062~id~4267268",
            "esrever": "8627624~di~260-V-RGV-لدم-رآ-یج-یو-نز-طخ-حالصا-نیشام_تاصخشم/",
            "image": "https://files.emalls.ir/files/Products/automatic/4267268/h5htdqus_thumb2.jpg",
            "category": null,
            "rate": null,
            "offcount": "36",
            "price": "۶۹۰,۰۰۰",
            "pprice": null,
            "discountpercent": null,
            "maxprice": "۲,۱۵۰,۰۰۰",
            "lupdate": "(۷ ساعت پیش)",
            "buyTitle": "",
            "buyLink": "",
            "spec": false,
            "used": false
        },
        {
            "id": 13630450,
            "title": "کیس گیمینگ Green مدل GRIFFIN G3",
            "titlefa": "کیس گیمینگ Green مدل GRIFFIN G3",
            "link": "/مشخصات_Case-Green-Griffin-G3-Gaming~id~13630450",
            "esrever": "05403631~di~gnimaG-3G-niffirG-neerG-esaC_تاصخشم/",
            "image": "https://files.emalls.ir/files/Products/automatic/13630450/qrxkdh0r_thumb2.jpg",
            "category": null,
            "rate": null,
            "offcount": "31",
            "price": "۳,۵۱۰,۰۰۰",
            "pprice": null,
            "discountpercent": null,
            "maxprice": "۵,۵۰۰,۰۰۰",
            "lupdate": "(۷ ساعت پیش)",
            "buyTitle": "",
            "buyLink": "",
            "spec": false,
            "used": false
        },
        {
            "id": 518745,
            "title": "چکش تخریب پوکا مدل 810",
            "titlefa": "Pukka 810 Demolition Hammer",
            "link": "/مشخصات_چکش-تخریب-پوکا-مدل-810~id~518745",
            "esrever": "547815~di~018-لدم-اکوپ-بیرخت-شکچ_تاصخشم/",
            "image": "https://files.emalls.ir/files/Products/automatic/518745/yjmfp4at_thumb2.jpg",
            "category": null,
            "rate": null,
            "offcount": "8",
            "price": "۴,۶۴۰,۰۰۰",
            "pprice": "۴,۹۸۵,۰۰۰",
            "discountpercent": "7",
            "maxprice": "۵,۴۰۰,۰۰۰",
            "lupdate": "(۷ ساعت پیش)",
            "buyTitle": "",
            "buyLink": "",
            "spec": false,
            "used": false
        },
        {
            "id": 236544,
            "title": "مینی واش فریدولین مدل SW25",
            "titlefa": "Feridolin Diaper Cleaner SW25",
            "link": "/مشخصات_مینی-واش-فریدولین-مدل-SW25~id~236544",
            "esrever": "445632~di~52WS-لدم-نیلودیرف-شاو-ینیم_تاصخشم/",
            "image": "https://files.emalls.ir/files/Products/automatic/236544/2f4boyuw_thumb2.jpg",
            "category": null,
            "rate": null,
            "offcount": "24",
            "price": "۲,۶۰۰,۰۰۰",
            "pprice": "۳,۹۵۰,۰۰۰",
            "discountpercent": "34",
            "maxprice": "۴,۵۵۸,۷۰۰",
            "lupdate": "(۷ ساعت پیش)",
            "buyTitle": "",
            "buyLink": "",
            "spec": false,
            "used": false
        },
        {
            "id": 2255490,
            "title": "کیس کامپیوتر گرین مدل Oraman Plus",
            "titlefa": "کیس کامپیوتر گرین مدل Oraman Plus",
            "link": "/مشخصات_Green-Oraman-Plus-Case~id~2255490",
            "esrever": "0945522~di~esaC-sulP-namarO-neerG_تاصخشم/",
            "image": "https://files.emalls.ir/files/Products/automatic/2255490/0jj1zvcb_thumb2.jpg",
            "category": null,
            "rate": null,
            "offcount": "60",
            "price": "۱,۴۱۰,۰۰۰",
            "pprice": null,
            "discountpercent": null,
            "maxprice": "۲,۲۶۶,۲۰۰",
            "lupdate": "(۷ ساعت پیش)",
            "buyTitle": "",
            "buyLink": "",
            "spec": false,
            "used": false
        }
    ],
    "lstpagingresualt": [
        {
            "page_number": "38",
            "link": "/%D9%84%DB%8C%D8%B3%D8%AA-%D9%82%DB%8C%D9%85%D8%AA~shop~1~o~1~page~38",
            "stat": "prev"
        },
        {
            "page_number": "39",
            "link": "",
            "stat": "current"
        },
        {
            "page_number": "40",
            "link": "/%D9%84%DB%8C%D8%B3%D8%AA-%D9%82%DB%8C%D9%85%D8%AA~shop~1~o~1~page~40",
            "stat": "next"
        }
    ],
    "sortlink": null,
    "pageurl": "/لیست-قیمت~shop~1~o~1~page~39",
    "pagetitle": "همه محصولات  فروشگاه دیجی کالا  امروز (۰۷ بهمن) ",
    "brandid": 0,
    "iua": false,
    "hidespecial": true,
    "sidelinks": [
        {
            "Url": "/لیست-قیمت_کامپیوتر~Category~316",
            "Title": "کامپیوتر",
            "Active": false,
            "First": true
        },
        {
            "Url": "/لیست-قیمت_All-in-One~Category~318",
            "Title": "All-in-One",
            "Active": false,
            "First": false
        },
        {
            "Url": "/لیست-قیمت_ست-گیمینگ~Category~596247",
            "Title": "ست گیمینگ",
            "Active": false,
            "First": false
        },
        {
            "Url": "/لیست-قیمت_مادربرد-MotherBoard~Category~339",
            "Title": "مادربرد",
            "Active": false,
            "First": false
        },
        {
            "Url": "/لیست-قیمت_پردازنده~Category~343",
            "Title": "پردازنده",
            "Active": false,
            "First": false
        },
        {
            "Url": "/لیست-قیمت_پاور-Power~Category~348",
            "Title": "پاور کامپیوتر ",
            "Active": false,
            "First": false
        },
        {
            "Url": "/لیست-قیمت_کارت-گرافیگ-VGA-Card~Category~354",
            "Title": "کارت گرافیک",
            "Active": false,
            "First": false
        },
        {
            "Url": "/لیست-قیمت_پرینتر~Category~202",
            "Title": "پرینتر",
            "Active": false,
            "First": false
        },
        {
            "Url": "/لیست-قیمت_ماوس~Category~210",
            "Title": "ماوس",
            "Active": false,
            "First": false
        },
        {
            "Url": "/لیست-قیمت_کیبورد~Category~211",
            "Title": "کیبورد",
            "Active": false,
            "First": false
        },
        {
            "Url": "/لیست-قیمت_وب-کم~Category~212",
            "Title": "وب کم",
            "Active": false,
            "First": false
        },
        {
            "Url": "/لیست-قیمت_مانیتور~Category~188",
            "Title": "مانیتور",
            "Active": false,
            "First": false
        },
        {
            "Url": "/لیست-قیمت_مانیتور-صنعتی-~Category~10992",
            "Title": "مانیتور صنعتی ",
            "Active": false,
            "First": false
        },
        {
            "Url": "/لیست-قیمت_فن-پردازنده~Category~267",
            "Title": "فن پردازنده",
            "Active": false,
            "First": false
        },
        {
            "Url": "/لیست-قیمت_فن-کارت-گرافیک~Category~45297",
            "Title": "فن کارت گرافیک",
            "Active": false,
            "First": false
        },
        {
            "Url": "/لیست-قیمت_اسکنر~Category~615",
            "Title": "اسکنر",
            "Active": false,
            "First": false
        },
        {
            "Url": "/لیست-قیمت_فن-کیس~Category~4187",
            "Title": "فن کیس",
            "Active": false,
            "First": false
        },
        {
            "Url": "/لیست-قیمت_کیس~Category~627",
            "Title": "کیس",
            "Active": true,
            "First": false
        },
        {
            "Url": "/لیست-قیمت_رم-سرور-~Category~39116",
            "Title": "رم سرور ",
            "Active": false,
            "First": false
        },
        {
            "Url": "/لیست-قیمت_کامپیوتر-سرور~Category~908",
            "Title": "کامپیوتر سرور",
            "Active": false,
            "First": false
        },
        {
            "Url": "/لیست-قیمت_رم-ریدر~Category~610",
            "Title": "رم ریدر",
            "Active": false,
            "First": false
        },
        {
            "Url": "/لیست-قیمت_کامپیوتر-کوچک~Category~1864",
            "Title": "کامپیوتر کوچک",
            "Active": false,
            "First": false
        },
        {
            "Url": "/لیست-قیمت_کامپیوتر-جمع-آوری-شده~Category~1976",
            "Title": "کامپیوتر جمع آوری شده",
            "Active": false,
            "First": false
        },
        {
            "Url": "/لیست-قیمت_دی-وی-دی-رایتر~Category~4179",
            "Title": "دی وی دی رایتر",
            "Active": false,
            "First": false
        },
        {
            "Url": "/لیست-قیمت_کارت-صدا~Category~4186",
            "Title": "کارت صدا",
            "Active": false,
            "First": false
        },
        {
            "Url": "/لیست-قیمت_ست-دسکتاپ-(ماوس-و-کیبورد)~Category~11123",
            "Title": "ست دسکتاپ (ماوس و کیبورد)",
            "Active": false,
            "First": false
        },
        {
            "Url": "/لیست-قیمت_کنترل-کننده-فن~Category~25336",
            "Title": "کنترل کننده فن",
            "Active": false,
            "First": false
        },
        {
            "Url": "/لیست-قیمت_خمیر-سیلیکونی-و-حرارتی~Category~10249",
            "Title": "خمیر سیلیکونی و حرارتی",
            "Active": false,
            "First": false
        },
        {
            "Url": "/لیست-قیمت_رم-کامپیوتر~Category~1861",
            "Title": "رم کامپیوتر",
            "Active": false,
            "First": false
        },
        {
            "Url": "/لیست-قیمت_کارت-کپچر~Category~46557",
            "Title": "کارت کپچر",
            "Active": false,
            "First": false
        },
        {
            "Url": "/لیست-قیمت_داپلیکیتور~Category~38902",
            "Title": "داپلیکیتور",
            "Active": false,
            "First": false
        },
        {
            "Url": "/لیست-قیمت_دستگاه-لمینیت-~Category~42584",
            "Title": "دستگاه لمینیت ",
            "Active": false,
            "First": false
        },
        {
            "Url": "/لیست-قیمت_دستگاه-صحافی~Category~42585",
            "Title": "دستگاه صحافی",
            "Active": false,
            "First": false
        },
        {
            "Url": "/لیست-قیمت_مادربرد-لپ-تاپ~Category~70320",
            "Title": "مادربرد لپ تاپ",
            "Active": false,
            "First": false
        },
        {
            "Url": "/لیست-قیمت_فن-پردازنده-ی-لپ-تاپ-~Category~72235",
            "Title": "فن پردازنده ی لپ تاپ ",
            "Active": false,
            "First": false
        },
        {
            "Url": "/لیست-قیمت_-لولای-لپ-تاپ-~Category~72236",
            "Title": " لولای لپ تاپ ",
            "Active": false,
            "First": false
        },
        {
            "Url": "/لیست-قیمت_مینی-کیس~Category~440534",
            "Title": "مینی کیس",
            "Active": false,
            "First": false
        }
    ],
    "pagetype": "pricelist.aspx",
    "canonical": "/%D9%84%DB%8C%D8%B3%D8%AA-%D9%82%DB%8C%D9%85%D8%AA~shop~1~page~39",
    "breadcrumbs": "<ol class='breadcrumb' vocab='http://schema.org/' typeof='BreadcrumbList'><li class='breadcrumb-item' property='itemListElement' typeof='ListItem'><a property='item' typeof='WebPage' href='/' id='/'><svg id='SvgBreadCrumbIcon' width='18' height='18' viewBox='0 0 18 18' fill='none' xmlns='http://www.w3.org/2000/svg'><path d='M8.93754 12.2713C7.79265 12.2713 7.22363 12.8403 7.22363 13.9852V15.6991H10.6514V13.9852C10.6514 12.8403 10.0824 12.2713 8.93754 12.2713Z' stroke='currentColor' stroke-width='1.37113' stroke-linecap='round' stroke-linejoin='round'></path><path d='M2.77441 8.30872V11.3869C2.77441 14.4651 4.00843 15.6991 7.0866 15.6991H10.7818C13.86 15.6991 15.094 14.4651 15.094 11.3869V8.30872' stroke='currentColor' stroke-width='1.37113' stroke-linecap='round' stroke-linejoin='round'></path><path d='M8.93785 8.84348C10.1924 8.84348 11.1179 7.82199 10.9945 6.56741L10.5421 1.98785H7.34048L6.88116 6.56741C6.75776 7.82199 7.68327 8.84348 8.93785 8.84348Z' stroke='currentColor' stroke-width='1.37113' stroke-linecap='round' stroke-linejoin='round'></path><path d='M13.2628 8.84348C14.6476 8.84348 15.6622 7.71916 15.5251 6.34118L15.3332 4.45588C15.0864 2.67342 14.4008 1.98785 12.6046 1.98785H10.5137L10.9936 6.79365C11.1101 7.92483 12.1316 8.84348 13.2628 8.84348Z' stroke='currentColor' stroke-width='1.37113' stroke-linecap='round' stroke-linejoin='round'></path><path d='M4.5775 8.84348C5.70868 8.84348 6.73017 7.92483 6.83986 6.79365L6.99068 5.27856L7.31975 1.98785H5.22879C3.43261 1.98785 2.74705 2.67342 2.50025 4.45588L2.31515 6.34118C2.17803 7.71916 3.19267 8.84348 4.5775 8.84348Z' stroke='currentColor' stroke-width='1.37113' stroke-linecap='round' stroke-linejoin='round'></path></svg>ایمالز</span></a><meta property='position' content='1'></li><li class='breadcrumb-item' property='itemListElement' typeof='ListItem'><a id='/Shops/' property='item' typeof='WebPage' href='/Shops/'><span property='name'>فروشگاه‌ها</span></a><meta property='position' ></li><li class='breadcrumb-item' property='itemListElement' typeof='ListItem'><a id='/%D9%84%DB%8C%D8%B3%D8%AA-%D9%82%DB%8C%D9%85%D8%AA~shop~1' property='item' typeof='WebPage' href='/%D9%84%DB%8C%D8%B3%D8%AA-%D9%82%DB%8C%D9%85%D8%AA~shop~1'><span property='name'>دیجی کالا</span></a><meta property='position' ></li></ol>"
}